statickg/__init__.py
statickg/__main__.py
statickg/helper.py
statickg/main.py
statickg/models/__init__.py
statickg/models/etl.py
statickg/models/file_and_path.py
statickg/models/prelude.py
statickg/models/repository.py
statickg/services/__init__.py
statickg/services/concat.py
statickg/services/copy.py
statickg/services/data_loader.py
statickg/services/drepr.py
statickg/services/drepr_upd.py
statickg/services/filter.py
statickg/services/fuseki.py
statickg/services/interface.py
statickg/services/sh.py
statickg/services/split.py
statickg/services/version.py
statickg-1.13.2.dist-info/METADATA
statickg-1.13.2.dist-info/WHEEL
statickg-1.13.2.dist-info/RECORD
