Metadata-Version: 2.4
Name: statickg
Version: 1.13.2
Summary: Tools for creating & running knowledge graphs from files
License: MIT
Author: Binh Vu
Author-email: bvu687@gmail.com
Requires-Python: >=3.11,<4.0
Classifier: License :: OSI Approved :: MIT License
Classifier: Programming Language :: Python :: 3
Classifier: Programming Language :: Python :: 3.11
Classifier: Programming Language :: Python :: 3.12
Classifier: Programming Language :: Python :: 3.13
Classifier: Programming Language :: Python :: 3.14
Requires-Dist: drepr-v2 (>=1.6.5,<2.0.0)
Requires-Dist: hugedict (>=2.14.1,<3.0.0)
Requires-Dist: joblib (>=1.4.2,<2.0.0)
Requires-Dist: libactor (>=2.0.1,<3.0.0)
Requires-Dist: loguru (>=0.7.0,<0.8.0)
Requires-Dist: orjson (>=3.10.3,<4.0.0)
Requires-Dist: python-slugify (>=8.0.4,<9.0.0)
Requires-Dist: requests (>=2.32.3,<3.0.0)
Requires-Dist: typer (>=0.19.2,<0.20.0)
Requires-Dist: xxhash (>=3.5.0,<4.0.0)
